dudek/__init__.py
dudek/config.py
dudek/opt.py
dudek/data/__init__.py
dudek/data/team_bas.py
dudek/ml/__init__.py
dudek/ml/data/__init__.py
dudek/ml/data/tdeed.py
dudek/ml/model/__init__.py
dudek/ml/model/common.py
dudek/ml/model/tdeed/__init__.py
dudek/ml/model/tdeed/eval/__init__.py
dudek/ml/model/tdeed/eval/base.py
dudek/ml/model/tdeed/eval/legacy.py
dudek/ml/model/tdeed/eval/two_heads.py
dudek/ml/model/tdeed/modules/__init__.py
dudek/ml/model/tdeed/modules/layers.py
dudek/ml/model/tdeed/modules/shift.py
dudek/ml/model/tdeed/modules/tdeed.py
dudek/ml/model/tdeed/training/__init__.py
dudek/ml/model/tdeed/training/two_heads.py
dudek/scripts/__init__.py
dudek/scripts/extract.py
dudek/scripts/tdeed.py
dudek/utils/__init__.py
dudek/utils/common.py
dudek/utils/frames.py
dudek/utils/ml.py
dudek/utils/video.py
dude_k-0.1.1.dist-info/METADATA
dude_k-0.1.1.dist-info/WHEEL
dude_k-0.1.1.dist-info/entry_points.txt
dude_k-0.1.1.dist-info/top_level.txt
dude_k-0.1.1.dist-info/RECORD
