Metadata-Version: 2.2
Name: dude.k
Version: 0.1.1
Summary: 2025 SoccerNet challenge development kit
Requires-Python: >=3.10
Requires-Dist: click>=8.1.7
Requires-Dist: huggingface-hub>=0.26.2
Requires-Dist: jsonlines>=4.0.0
Requires-Dist: kornia>=0.7.4
Requires-Dist: moviepy>=2.1.1
Requires-Dist: opencv-python>=4.10.0.84
Requires-Dist: pandas>=2.2.3
Requires-Dist: python-dotenv>=1.0.1
Requires-Dist: python-slugify>=8.0.4
Requires-Dist: soccernet>=0.1.61
Requires-Dist: tensorboard>=2.18.0
Requires-Dist: timm>=1.0.12
Requires-Dist: torch>=2.5.1
Requires-Dist: torchvision>=0.20.1
Requires-Dist: wandb>=0.19.1
